flake8_fastapi/__init__.py
flake8_fastapi/errors.py
flake8_fastapi/plugin.py
flake8_fastapi/py.typed
flake8_fastapi/visitors/__init__.py
flake8_fastapi/visitors/cors_middleware.py
flake8_fastapi/visitors/generic_exception_handler.py
flake8_fastapi/visitors/no_content_response.py
flake8_fastapi/visitors/route_decorator.py
flake8_fastapi/visitors/router_prefix.py
flake8_fastapi/visitors/undocumented_exception.py
flake8_fastapi-0.6.1.dist-info/entry_points.txt
flake8_fastapi-0.6.1.dist-info/LICENSE
flake8_fastapi-0.6.1.dist-info/WHEEL
flake8_fastapi-0.6.1.dist-info/METADATA
flake8_fastapi-0.6.1.dist-info/RECORD
