Metadata-Version: 2.1
Name: flake8-fastapi
Version: 0.6.1
Summary: flake8 plugin that checks FastAPI code against opiniated style rules 🤓
Home-page: https://github.com/Kludex/flake8-fastapi
License: MIT
Author: Marcelo Trylesinski
Author-email: marcelotryle@gmail.com
Requires-Python: >=3.8,<4.0
Classifier: Intended Audience :: Developers
Classifier: License :: OSI Approved :: MIT License
Classifier: Operating System :: OS Independent
Classifier: Programming Language :: Python
Classifier: Programming Language :: Python :: 3
Classifier: Programming Language :: Python :: 3 :: Only
Classifier: Programming Language :: Python :: 3.8
Classifier: Programming Language :: Python :: 3.9
Classifier: Topic :: Software Development :: Build Tools
Classifier: Topic :: Software Development :: Libraries :: Python Modules
Requires-Dist: fastapi (>=0.65.1,<0.66.0)
Requires-Dist: flake8-plugin-utils (>=1.3.2,<2.0.0)
Project-URL: Repository, https://github.com/Kludex/flake8-fastapi
